{
  "tenants": [
    {
      "id": "1",
      "name": "Clyde",
      "apartment": "Tilburg",
      "House no.": "Tilb 03",
      "rent": "2000",
      "modeofpayment": "money transfer"
    },
    {
      "id": "2",
      "name": "Kimberly",
      "apartment": "Tilburg",
      "House no.": "Tilb 16",
      "rent": "2000",
      "modeofpayment": "mpesa"
    },
    {
      "id": "3",
      "name": "Tehila",
      "apartment": "Euniza",
      "House no.": "Ez 11",
      "rent": "1000",
      "modeofpayment": "money transfer"
    },
    {
      "id": "4",
      "name": "Dylan",
      "apartment": "Euniza",
      "House no.": "Ez 17",
      "rent": "1000",
      "modeofpayment": "money transfer"
    },
    {
      "id": "5",
      "name": "Mikayler",
      "apartment": "Euniza",
      "House no.": "Ez 21",
      "rent": "1500",
      "modeofpayment": "credit card"
    },
    {
      "id": "bd11",
      "name": "Imani",
      "rent": "2000",
      "modeofpayment": "mpesa"
    }
  ]
}